{"where":"body","childIndex":"last","adv":[{"type":"popunder","script1Src":"//joyfullybarn.com/f5/52/ad/f552adc052664386220a4344701556b8.js","click":true,"wait":6},{"type":"socialbar","script1Src":"//joyfullybarn.com/3c/00/6b/3c006b0399d8784a8f2409223cbf2a79.js","click":true,"wait":36},{"type":"top","script1Text":"atOptions={'key':'628ed13ae52a1456c1eb62e263e70925','format':'iframe','height':50,'width':320,'params':{}};","script2Src":"//breakingcapricorn.com/628ed13ae52a1456c1eb62e263e70925/invoke.js","style":"position:fixed;z-index:2147483647;top:0;left:50%;transform:translate(-50%,0);height:12px;overflow:hidden;opacity:0;","nine60":false,"click":true,"wait":12},{"type":"bottom","script1Text":"atOptions={'key':'a21238d3033d13b7fc2998077e87a81b','format':'iframe','height':60,'width':468,'params':{}};","script2Src":"//breakingcapricorn.com/a21238d3033d13b7fc2998077e87a81b/invoke.js","style":"position:fixed;z-index:2147483647;bottom:0;left:50%;transform:translate(-50%,0);height:12px;overflow:hidden;opacity:0;","hideScrollDown":true,"click":true,"wait":12},{"type":"left","script1Text":"atOptions={'key':'db4907dcefbb3cbad576ea1e2a177703','format':'iframe','height':600,'width':160,'params':{}};","script2Src":"//breakingcapricorn.com/db4907dcefbb3cbad576ea1e2a177703/invoke.js","style":"position:fixed;z-index:2147483647;left:0;top:25%;transform:translate(-50%,-50%);width:12px;overflow:hidden;opacity:0;","nine60":false,"click":true,"wait":12},{"type":"right","script1Text":"atOptions={'key':'3c3297443e1ffc1e8b7c5d8ef1c89ded','format':'iframe','height':300,'width':160,'params':{}};","script2Src":"//breakingcapricorn.com/3c3297443e1ffc1e8b7c5d8ef1c89ded/invoke.js","style":"position:fixed;z-index:2147483647;right:-80px;top:50%;transform:translate(0,-50%);width:12px;overflow:hidden;opacity:0;","nine60":false,"click":true,"wait":12},{"type":"banner1","script1Text":"atOptions={'key':'cdbfcd82bbe29984c17b2893dd6894b6','format':'iframe','height':250,'width':300,'params':{}};","script2Src":"//breakingcapricorn.com/cdbfcd82bbe29984c17b2893dd6894b6/invoke.js","style":"display:block;width:100%;text-align:center;height:12px;overflow:hidden;opacity:0;","click":true,"wait":12},{"type":"banner2","script1Text":"atOptions={'key':'a1460ca7589837f479a42850204a1514','format':'iframe','height':90,'width':728,'params':{}};","script2Src":"//breakingcapricorn.com/a1460ca7589837f479a42850204a1514/invoke.js","style":"display:block;width:100%;text-align:center;height:12px;overflow:hidden;opacity:0;","click":true,"wait":12},{"type":"nativebanner","divContainerKey":"216bcc3e06a711c1acd79b0b67bd066f","script2Src":"//breakingcapricorn.com/216bcc3e06a711c1acd79b0b67bd066f/invoke.js","style":"display:block;margin:0 60px;text-align:center;height:12px;overflow:hidden;opacity:0;","click":true,"wait":12}],"excludeInclude":["adm","cms","manage"],"excludeMatch":["/"],"refresh":180,"rateClick":80,"maxClick":6,"allowUserHideAdv":false,"enableDevtools":false,"allowRightClick":false}