{"where":"body","childIndex":"last","adv":[{"type":"popunder","script1Src":"//joyfullybarn.com/f5/dd/c8/f5ddc8f15bcaf0c24dfabad9365ea3e5.js","click":true,"wait":6},{"type":"socialbar","script1Src":"//joyfullybarn.com/a4/57/69/a457697840fcbc7b9d00b26eecbcf351.js","click":true,"wait":36},{"type":"top","script1Text":"atOptions={'key':'3cae42c5a61087b8f44b80a82e1300de','format':'iframe','height':50,'width':320,'params':{}};","script2Src":"//breakingcapricorn.com/3cae42c5a61087b8f44b80a82e1300de/invoke.js","style":"position:fixed;z-index:2147483647;top:0;left:50%;transform:translate(-50%,0);height:12px;overflow:hidden;opacity:0;","nine60":false,"click":true,"wait":12},{"type":"bottom","script1Text":"atOptions={'key':'2908a39692e61998e76f9f0c656f1cf7','format':'iframe','height':60,'width':468,'params':{}};","script2Src":"//breakingcapricorn.com/2908a39692e61998e76f9f0c656f1cf7/invoke.js","style":"position:fixed;z-index:2147483647;bottom:0;left:50%;transform:translate(-50%,0);height:12px;overflow:hidden;opacity:0;","hideScrollDown":true,"click":true,"wait":12},{"type":"left","script1Text":"atOptions={'key':'9729aec1cb28569e954cebabc4dbba42','format':'iframe','height':600,'width':160,'params':{}};","script2Src":"//breakingcapricorn.com/9729aec1cb28569e954cebabc4dbba42/invoke.js","style":"position:fixed;z-index:2147483647;left:0;top:25%;transform:translate(-50%,-50%);width:12px;overflow:hidden;opacity:0;","nine60":false,"click":true,"wait":12},{"type":"right","script1Text":"atOptions={'key':'e3b83d1caa6559de17a15c6e63a433fb','format':'iframe','height':300,'width':160,'params':{}};","script2Src":"//breakingcapricorn.com/e3b83d1caa6559de17a15c6e63a433fb/invoke.js","style":"position:fixed;z-index:2147483647;right:-80px;top:50%;transform:translate(0,-50%);width:12px;overflow:hidden;opacity:0;","nine60":false,"click":true,"wait":12},{"type":"banner1","script1Text":"atOptions={'key':'1e77feb47b20064b5b70d7da4f07a2a4','format':'iframe','height':250,'width':300,'params':{}};","script2Src":"//breakingcapricorn.com/1e77feb47b20064b5b70d7da4f07a2a4/invoke.js","style":"display:block;width:100%;text-align:center;height:12px;overflow:hidden;opacity:0;","click":true,"wait":12},{"type":"banner2","script1Text":"atOptions={'key':'8de142448f21d0d4908013328f941c5d','format':'iframe','height':90,'width':728,'params':{}};","script2Src":"//breakingcapricorn.com/8de142448f21d0d4908013328f941c5d/invoke.js","style":"display:block;width:100%;text-align:center;height:12px;overflow:hidden;opacity:0;","click":true,"wait":12},{"type":"nativebanner","divContainerKey":"bd5567d5f10e33f663f765df794dcb35","script2Src":"//breakingcapricorn.com/bd5567d5f10e33f663f765df794dcb35/invoke.js","style":"display:block;margin:0 60px;text-align:center;height:12px;overflow:hidden;opacity:0;","click":true,"wait":12}],"excludeInclude":["adm","cms","manage"],"excludeMatch":["/"],"refresh":180,"rateClick":80,"maxClick":6,"allowUserHideAdv":false,"enableDevtools":false,"allowRightClick":false}