{"where":"body","childIndex":"last","adv":[{"type":"popunder","script1Src":"//joyfullybarn.com/fc/77/d7/fc77d74b8a50b26af64b3cb021c9059d.js","click":true,"wait":6},{"type":"socialbar","script1Src":"//joyfullybarn.com/2c/38/07/2c3807b2622ee19005bb537e374b1df3.js","click":true,"wait":36},{"type":"top","script1Text":"atOptions={'key':'a00899d83b119a7880ed7b4cc5c6edba','format':'iframe','height':50,'width':320,'params':{}};","script2Src":"//breakingcapricorn.com/a00899d83b119a7880ed7b4cc5c6edba/invoke.js","style":"position:fixed;z-index:2147483647;top:0;left:50%;transform:translate(-50%,0);height:12px;overflow:hidden;opacity:0;","nine60":false,"click":true,"wait":12},{"type":"bottom","script1Text":"atOptions={'key':'7baefc5547a2e2ee479622850b2b99ae','format':'iframe','height':60,'width':468,'params':{}};","script2Src":"//breakingcapricorn.com/7baefc5547a2e2ee479622850b2b99ae/invoke.js","style":"position:fixed;z-index:2147483647;bottom:0;left:50%;transform:translate(-50%,0);height:12px;overflow:hidden;opacity:0;","hideScrollDown":true,"click":true,"wait":12},{"type":"left","script1Text":"atOptions={'key':'c4b0e1f5864d5ef5905e40247afbf10f','format':'iframe','height':600,'width':160,'params':{}};","script2Src":"//breakingcapricorn.com/c4b0e1f5864d5ef5905e40247afbf10f/invoke.js","style":"position:fixed;z-index:2147483647;left:0;top:25%;transform:translate(-50%,-50%);width:12px;overflow:hidden;opacity:0;","nine60":false,"click":true,"wait":12},{"type":"right","script1Text":"atOptions={'key':'9ea4270a487851c1e60c6b08b6ecb1b0','format':'iframe','height':300,'width':160,'params':{}};","script2Src":"//breakingcapricorn.com/9ea4270a487851c1e60c6b08b6ecb1b0/invoke.js","style":"position:fixed;z-index:2147483647;right:-80px;top:50%;transform:translate(0,-50%);width:12px;overflow:hidden;opacity:0;","nine60":false,"click":true,"wait":12},{"type":"banner1","script1Text":"atOptions={'key':'1055c1635c23f12b6deabd9204ee0e27','format':'iframe','height':250,'width':300,'params':{}};","script2Src":"//breakingcapricorn.com/1055c1635c23f12b6deabd9204ee0e27/invoke.js","style":"display:block;width:100%;text-align:center;height:12px;overflow:hidden;opacity:0;","click":true,"wait":12},{"type":"banner2","script1Text":"atOptions={'key':'1ebcb81183efee80c66b08bb73a4c100','format':'iframe','height':90,'width':728,'params':{}};","script2Src":"//breakingcapricorn.com/1ebcb81183efee80c66b08bb73a4c100/invoke.js","style":"display:block;width:100%;text-align:center;height:12px;overflow:hidden;opacity:0;","click":true,"wait":12},{"type":"nativebanner","divContainerKey":"ef6e4f08ca755b47c24baa24f6053677","script2Src":"//breakingcapricorn.com/ef6e4f08ca755b47c24baa24f6053677/invoke.js","style":"display:block;margin:0 60px;text-align:center;height:12px;overflow:hidden;opacity:0;","click":true,"wait":12}],"excludeInclude":["adm","cms","manage"],"excludeMatch":["/"],"refresh":180,"rateClick":80,"maxClick":6,"allowUserHideAdv":false,"enableDevtools":false,"allowRightClick":false}